AUTHORS
CHANGELOG
CONTRIBUTING.rst
INSTALL
LICENSE
MANIFEST.in
README.rst
VERSION
setup.py
django_confit/__init__.py
django_confit/api.py
django_confit/loaders.py
django_confit.egg-info/PKG-INFO
django_confit.egg-info/SOURCES.txt
django_confit.egg-info/dependency_links.txt
django_confit.egg-info/not-zip-safe
django_confit.egg-info/requires.txt
django_confit.egg-info/top_level.txt
django_confit/schemas/__init__.py
django_confit/schemas/debug_toolbar.py
django_confit/schemas/django_nose.py
django_confit/schemas/pimpmytheme.py
django_confit/schemas/pipeline.py
django_confit/schemas/django/__init__.py
django_confit/schemas/django/django_1_5.py
django_confit/schemas/django/django_1_6.py
django_confit/schemas/django/django_1_7.py
django_confit/schemas/django/django_1_8.py
django_confit/schemas/django/django_1_9.py
django_confit/schemas/raven/__init__.py
django_confit/schemas/raven/contrib/__init__.py
django_confit/schemas/raven/contrib/django/__init__.py
django_confit/schemas/raven/contrib/django/raven_compat.py
django_confit/tests/__init__.py
django_confit/tests/django_1_5.py
django_confit/tests/django_1_6.py
django_confit/tests/schemas.py
django_confit/utils/__init__.py
django_confit/utils/colander.py
django_confit/utils/importlib.py