Metadata-Version: 1.1
Name: django-confit
Version: 0.6
Summary: Django settings loaders and validators, with local flavour.
Home-page: https://django-confit.readthedocs.org
Author: Benoît Bryon
Author-email: benoit@marmelune.net
License: BSD
Keywords: configuration settings schema validation yaml json
Platform: UNKNOWN
Classifier: Development Status :: 3 - Alpha
Classifier: License :: OSI Approved :: BSD License
Classifier: Programming Language :: Python :: 2.7
Classifier: Programming Language :: Python :: 3.3
Classifier: Framework :: Django
